Metadata-Version: 1.1
Name: getboxplots
Version: 0.0.1
Summary: data visualisation
Home-page: UNKNOWN
Author: Akash Sathe
Author-email: akashsathe79@gmail.com
License: MIT
Keywords: boxplots
Platform: UNKNOWN
Classifier: Development Status :: 5 - Production/Stable
Classifier: Intended Audience :: Education
Classifier: Operating System :: Microsoft :: Windows :: Windows 10
Classifier: License :: OSI Approved :: MIT License
Classifier: Programming Language :: Python :: 3
